{
    "questions": [
        {
            "grade": 7,
            "subjects": [
                {
                    "key": "math",
                    "chineseName": "数学",
                    "questions": [
                        {
                            "passage": "毛毛很喜欢音乐，但是不太喜欢数学。他觉得数学没有用。",
                            "question": "毛毛喜欢数学吗？",
                            "answers": ["毛毛很喜欢", "毛毛不喜欢"],
                            "answerIndex": 1
                        }
                    ]
                },
                {
                    "key": "history",
                    "chineseName": "历史",
                    "questions": [
                        {
                            "question": "World War 2 在历史里面学的。",
                            "answers": ["对", "错"],
                            "answerIndex": 0
                        }
                    ]
                },
                {
                    "key": "spanish",
                    "chineseName": "西班牙语",
                    "questions": [
                        {
                            "question": "中国人都会说西班牙语。",
                            "answers": ["对", "错"],
                            "answerIndex": 1
                        }
                    ]
                },
                {
                    "key": "geography",
                    "chineseName": "地理",
                    "questions": [
                        {
                            "passage": "地理是好天的第三节课。音乐课在地理课之后。",
                            "question": "好天的第四课是什么？",
                            "answers": ["外语", "英语", "地理"],
                            "answerIndex": 2
                        }
                    ]
                },
                {
                    "key": "martialarts",
                    "chineseName": "美术",
                    "questions": [
                        {
                            "question": "画画是美术吗？",
                            "answers": ["是", "不是"],
                            "answerIndex": 1
                        }
                    ]
                },
                {
                    "key": "drama",
                    "chineseName": "戏剧",
                    "questions": [
                        {
                            "question": "你现在在上戏剧课吗？",
                            "answers": ["不在", "在"],
                            "answerIndex": 0
                        }
                    ]
                },
                {
                    "key": "music",
                    "chineseName": "音乐",
                    "questions": [
                        {
                            "passage": "好天上数学，音乐，和戏剧。",
                            "question": "好天上应约课吗？",
                            "answers": ["不上", "上"],
                            "answerIndex": 1
                        }
                    ]
                }
            ]
        },
        {
            "grade": 8,
            "subjects": [
                {
                    "key": "math",
                    "chineseName": "数学",
                    "questions": [
                        {
                            "passage": "妈妈从来不做数学因为他不上学。他对数学不感兴趣。",
                            "question": "妈妈的兴趣是什么？",
                            "answers": ["数学", "英语", "我们不知道"],
                            "answerIndex": 2
                        }
                    ]
                },
                {
                    "key": "english",
                    "chineseName": "英语",
                    "questions": [
                        {
                            "question": "陈老师教英语吗？",
                            "answers": ["教", "不教"],
                            "answerIndex": 1
                        }
                    ]
                },
                {
                    "key": "music",
                    "chineseName": "音乐",
                    "questions": [
                        {
                            "question": "TJ有音乐课吗？",
                            "answers": ["有", "没有"],
                            "answerIndex": 0
                        }
                    ]
                },
                {
                    "key": "geography",
                    "chineseName": "地理",
                    "questions": [
                        {
                            "passage": "好天很喜欢他的地理老师，花老师。花老师对她的学生很好。",
                            "question": "好天为什么喜欢花老师？",
                            "answers": ["花老师很漂亮", "花老师对他的学生很好", "花老师教数学"],
                            "answerIndex": 1
                        }
                    ]
                },
                {
                    "key": "german",
                    "chineseName": "德语",
                    "questions": [
                        {
                            "question": "你上德语吗？",
                            "answers": ["上", "不上"],
                            "answerIndex": 1
                        }
                    ]
                },
                {
                    "key": "science",
                    "chineseName": "科学",
                    "questions": [
                        {
                            "question": "我们上一个科学学校。",
                            "answers": ["对", "错"],
                            "answerIndex": 0
                        }
                    ]
                },
                {
                    "key": "law",
                    "chineseName": "法律",
                    "questions": [
                        {
                            "passage": "爸爸说法律很有趣。我觉得他错。",
                            "question": "他觉得法律有趣吗？",
                            "answers": ["很有趣", "没有趣"],
                            "answerIndex": 1
                        }
                    ]
                }
            ]
        }
    ]
}
